aserto_authorizer_grpc/__init__.py
aserto_authorizer_grpc/aserto/__init__.py
aserto_authorizer_grpc/aserto/api/__init__.py
aserto_authorizer_grpc/aserto/api/v1/__init__.py
aserto_authorizer_grpc/aserto/authorizer/__init__.py
aserto_authorizer_grpc/aserto/authorizer/authorizer/__init__.py
aserto_authorizer_grpc/aserto/authorizer/authorizer/v1/__init__.py
aserto_authorizer_grpc/aserto/options/__init__.py
aserto_authorizer_grpc/aserto/options/v1/__init__.py
aserto_authorizer_grpc/google/__init__.py
aserto_authorizer_grpc/google/api/__init__.py
aserto_authorizer_grpc/grpc/__init__.py
aserto_authorizer_grpc/grpc/gateway/__init__.py
aserto_authorizer_grpc/grpc/gateway/protoc_gen_openapiv2/__init__.py
aserto_authorizer_grpc/grpc/gateway/protoc_gen_openapiv2/options/__init__.py
aserto_authorizer_grpc/py.typed
aserto_authorizer_grpc-0.3.1.dist-info/WHEEL
aserto_authorizer_grpc-0.3.1.dist-info/METADATA
aserto_authorizer_grpc-0.3.1.dist-info/RECORD
