Metadata-Version: 2.1
Name: aserto-authorizer-grpc
Version: 0.3.1
Summary: gRPC client for Aserto Authorizer service instances
Home-page: https://github.com/aserto-dev/aserto-python/tree/HEAD/packages/aserto-authorizer-grpc
License: Apache-2.0
Author: Aserto, Inc.
Author-email: pypi@aserto.com
Maintainer: authereal
Maintainer-email: authereal@aserto.com
Requires-Python: >=3.7,<4.0
Classifier: Intended Audience :: Developers
Classifier: License :: OSI Approved :: Apache Software License
Classifier: Operating System :: OS Independent
Classifier: Programming Language :: Python
Classifier: Programming Language :: Python :: 3
Classifier: Programming Language :: Python :: 3 :: Only
Classifier: Programming Language :: Python :: 3.7
Classifier: Programming Language :: Python :: 3.8
Classifier: Programming Language :: Python :: 3.9
Classifier: Topic :: Software Development :: Libraries
Classifier: Typing :: Typed
Requires-Dist: betterproto (==v2.0.0b4)
Requires-Dist: certifi (>=2021.5.30,<2022.0.0)
Requires-Dist: typing-extensions (>=3.10.0,<4.0.0)
Project-URL: Documentation, https://github.com/aserto-dev/aserto-python/tree/HEAD/packages/aserto-authorizer-grpc
Project-URL: Repository, https://github.com/aserto-dev/aserto-python/tree/HEAD/packages/aserto-authorizer-grpc
